codex/__init__.py
codex/codexregius.py
codexregius-1.0.2.dist-info/METADATA
codexregius-1.0.2.dist-info/WHEEL
codexregius-1.0.2.dist-info/top_level.txt
codexregius-1.0.2.dist-info/RECORD
