Metadata-Version: 2.1
Name: codexregius
Version: 1.0.2
Summary: A simple debugging library
Home-page: https://github.com/StealthyPanda/codex/
Author: StealthyPanda
Author-email: shaikm259@gmail.com
Classifier: Programming Language :: Python :: 3
Classifier: License :: OSI Approved :: MIT License
Classifier: Operating System :: OS Independent
Requires-Python: >=3.10
